llm_discovery/__init__.py
llm_discovery/__main__.py
llm_discovery/constants.py
llm_discovery/exceptions.py
llm_discovery/cli/__init__.py
llm_discovery/cli/main.py
llm_discovery/cli/output.py
llm_discovery/cli/commands/__init__.py
llm_discovery/cli/commands/export.py
llm_discovery/cli/commands/list.py
llm_discovery/cli/commands/update.py
llm_discovery/data/anthropic_models.toml
llm_discovery/models/__init__.py
llm_discovery/models/config.py
llm_discovery/models/prebuilt.py
llm_discovery/models/provider.py
llm_discovery/services/__init__.py
llm_discovery/services/cache.py
llm_discovery/services/change_detector.py
llm_discovery/services/changelog_generator.py
llm_discovery/services/discovery.py
llm_discovery/services/prebuilt_loader.py
llm_discovery/services/snapshot.py
llm_discovery/services/exporters/__init__.py
llm_discovery/services/exporters/csv_exporter.py
llm_discovery/services/exporters/json_exporter.py
llm_discovery/services/exporters/markdown_exporter.py
llm_discovery/services/exporters/toml_exporter.py
llm_discovery/services/exporters/yaml_exporter.py
llm_discovery/services/fetchers/__init__.py
llm_discovery/services/fetchers/anthropic.py
llm_discovery/services/fetchers/base.py
llm_discovery/services/fetchers/google.py
llm_discovery/services/fetchers/openai.py
llm_discovery-0.1.0.dist-info/METADATA
llm_discovery-0.1.0.dist-info/WHEEL
llm_discovery-0.1.0.dist-info/entry_points.txt
llm_discovery-0.1.0.dist-info/licenses/LICENSE
llm_discovery-0.1.0.dist-info/RECORD
