Metadata-Version: 2.4
Name: llm-discovery
Version: 0.1.0
Summary: LLM model discovery and tracking system for real-time monitoring of available models across multiple providers
Author-email: driller <eleshis@gmail.com>
License: MIT
License-File: LICENSE
Keywords: ai,anthropic,cli,google,llm,model-discovery,monitoring,openai
Classifier: Development Status :: 3 - Alpha
Classifier: Intended Audience :: Developers
Classifier: License :: OSI Approved :: MIT License
Classifier: Programming Language :: Python :: 3
Classifier: Programming Language :: Python :: 3.13
Classifier: Topic :: Software Development :: Libraries :: Python Modules
Requires-Python: >=3.13
Requires-Dist: google-cloud-aiplatform>=1.70.0
Requires-Dist: google-generativeai>=0.8.0
Requires-Dist: httpx>=0.27.0
Requires-Dist: openai>=1.0.0
Requires-Dist: platformdirs>=4.0.0
Requires-Dist: pydantic>=2.0.0
Requires-Dist: pyyaml>=6.0.0
Requires-Dist: rich>=13.0.0
Requires-Dist: tomli-w>=1.2.0
Requires-Dist: typer>=0.15.0
Provides-Extra: dev
Requires-Dist: mypy>=1.13.0; extra == 'dev'
Requires-Dist: pytest-asyncio>=0.24.0; extra == 'dev'
Requires-Dist: pytest-cov>=6.0.0; extra == 'dev'
Requires-Dist: pytest>=8.0.0; extra == 'dev'
Requires-Dist: ruff>=0.8.0; extra == 'dev'
Provides-Extra: docs
Requires-Dist: myst-parser>=4.0.0; extra == 'docs'
Requires-Dist: sphinx-rtd-theme>=3.0.0; extra == 'docs'
Requires-Dist: sphinx>=8.0.0; extra == 'docs'
